DoRePy/__init__.py
DoRePy/dorepy.py
DoRePy-0.1.1.dist-info/LICENSE
DoRePy-0.1.1.dist-info/METADATA
DoRePy-0.1.1.dist-info/WHEEL
DoRePy-0.1.1.dist-info/entry_points.txt
DoRePy-0.1.1.dist-info/top_level.txt
DoRePy-0.1.1.dist-info/RECORD
