Metadata-Version: 2.1
Name: DoRePy
Version: 0.1.1
Summary: A tool for downloading files with filenames matching user-specified regex patterns which are linked to on a user-provided URL
Home-page: https://github.com/CillySu/DoRePy
Author: Cillian Scott
Author-email: scottci@tcd.ie
Requires-Python: >=3.6
License-File: LICENSE
Requires-Dist: requests
Requires-Dist: beautifulsoup4
